setup.py
pyhaml_jinja/__init__.py
pyhaml_jinja/errors.py
pyhaml_jinja/haml_extension.py
pyhaml_jinja/parser.py
pyhaml_jinja/renderer.py
pyhaml_jinja.egg-info/PKG-INFO
pyhaml_jinja.egg-info/SOURCES.txt
pyhaml_jinja.egg-info/dependency_links.txt
pyhaml_jinja.egg-info/requires.txt
pyhaml_jinja.egg-info/top_level.txt
pyhaml_jinja.egg-info/zip-safe
pyhaml_jinja/nodes/__init__.py
pyhaml_jinja/nodes/childless_node.py
pyhaml_jinja/nodes/custom_block_node.py
pyhaml_jinja/nodes/empty_node.py
pyhaml_jinja/nodes/html_node.py
pyhaml_jinja/nodes/jinja_node.py
pyhaml_jinja/nodes/node.py
pyhaml_jinja/nodes/text_node.py