Metadata-Version: 1.1
Name: pyhaml-jinja
Version: 0.11-dev
Summary: Haml-style syntax for Jinja2 templates
Home-page: http://github.com/jgeewax/pyhaml-jinja
Author: JJ Geewax
Author-email: jj@geewax.org
License: UNKNOWN
Keywords: jinja2 templates haml html
Platform: any
Classifier: Development Status :: 4 - Beta
Classifier: Environment :: Web Environment
Classifier: Intended Audience :: Developers
Classifier: License :: OSI Approved :: BSD License
Classifier: Operating System :: OS Independent
Classifier: Programming Language :: Python
Classifier: Topic :: Internet :: WWW/HTTP :: Dynamic Content
Classifier: Topic :: Software Development :: Libraries :: Python Modules
Classifier: Topic :: Text Processing :: Markup :: HTML
